mrmath/__init__.py
mrmath/_const.py
mrmath/_hyperbol.py
mrmath/_numtheor.py
mrmath/py.typed
mrmath/vecmat3d.py
mrmath-0.2.0.dist-info/METADATA
mrmath-0.2.0.dist-info/WHEEL
mrmath-0.2.0.dist-info/top_level.txt
mrmath-0.2.0.dist-info/RECORD
