Metadata-Version: 2.1
Name: mrmath
Version: 0.2.0
Summary: Python Library for Mathematic Calculation
Home-page: https://anatas_ch.gitlab.io/pyl_mrmath/
Author: Michael Rippstein
Author-email: info@anatas.ch
License: AGPL-3.0
Project-URL: Documentation, https://mrmath.readthedocs.io/
Project-URL: Bug Tracker, https://gitlab.com/anatas_ch/pyl_mrmath/-/issues
Project-URL: Source Code, https://gitlab.com/anatas_ch/pyl_mrmath
Platform: UNKNOWN
Classifier: Development Status :: 3 - Alpha
Classifier: Intended Audience :: Developers
Classifier: License :: OSI Approved :: GNU Affero General Public License v3 or later (AGPLv3+)
Classifier: Topic :: Utilities
Classifier: Programming Language :: Python :: 3
Classifier: Programming Language :: Python :: 3.9
Classifier: Programming Language :: Python :: 3.10
Classifier: Programming Language :: Python :: Implementation :: CPython
Classifier: Programming Language :: Python :: Implementation :: PyPy
Classifier: Operating System :: OS Independent
Classifier: Typing :: Typed
Requires-Python: >=3.9
Requires-Dist: numpy (>=1.22.2)
